aiwebexplorer/__init__.py
aiwebexplorer/_version.py
aiwebexplorer/agent_factory.py
aiwebexplorer/agents.py
aiwebexplorer/config.py
aiwebexplorer/dependencies.py
aiwebexplorer/interfaces.py
aiwebexplorer/logger.py
aiwebexplorer/webexplorer.py
aiwebexplorer-0.0.3.dist-info/METADATA
aiwebexplorer-0.0.3.dist-info/WHEEL
aiwebexplorer-0.0.3.dist-info/top_level.txt
aiwebexplorer-0.0.3.dist-info/RECORD
