Metadata-Version: 2.4
Name: aiwebexplorer
Version: 0.0.3
Summary: An agent for agents to explore the web
Author-email: Francesco Vertemati <verte.fra@gmail.com>
Requires-Python: >=3.12
Requires-Dist: agno>=2.0.3
Requires-Dist: aiohttp>=3.12.15
Requires-Dist: bs4>=0.0.2
Requires-Dist: cachetools>=6.2.0
Requires-Dist: openai>=1.107.1
Requires-Dist: playwright>=1.55.0
Requires-Dist: playwright-stealth>=2.0.0
Requires-Dist: pydantic>=2.11.7
Requires-Dist: pydantic-settings>=2.10.1
Requires-Dist: structlog>=25.4.0
